my_logtool/__init__.py
my_logtool/my_logger.py
my_logtool-0.1.dist-info/LICENSE
my_logtool-0.1.dist-info/METADATA
my_logtool-0.1.dist-info/WHEEL
my_logtool-0.1.dist-info/top_level.txt
my_logtool-0.1.dist-info/RECORD
